{
  "sections": [
    {
      "title": "Mentoria em C# Completo",
      "cards": [
        {
          "title": "C# Completo",
          "badge": "mentoria privada",
          "status": "Disponível",
          "vagas": "8",
          "thumbnail": "http://codigodozero.com/webdata/imageteste.png",
          "description": "Mentoria completa para dominar C# do zero ao avançado, incluindo .NET.",
          "benefits": [
            "Aulas ao vivo e gravadas com foco em C# moderno",
            "Projetos reais com orientação individual",
            "Feedback direto do mentor via Discord",
            "Correção de código em tempo real",
            "Suporte exclusivo para dúvidas técnicas"
          ],
          "action_button": "Fazer aula grátis",
          "highlight": true
        }
      ]
    },
    {
      "title": "Mentoria Web Fullstack",
      "cards": [
        {
          "title": "Web Fullstack",
          "badge": "full acesso",
          "status": "Disponível",
          "vagas": "4",
          "thumbnail": "http://codigodozero.com/webdata/imageteste.png",
          "description": "Mentoria completa para se tornar um desenvolvedor web fullstack com práticas modernas de frontend e backend.",
          "benefits": [
            "Frontend com React, Tailwind e SPA",
            "Backend com Node.js, Express e MongoDB",
            "Integração total entre frontend e backend",
            "Hospedagem e deploy com Vercel e Railway",
            "Acompanhamento de projetos em tempo real"
          ],
          "action_button": "Fazer aula grátis",
          "highlight": true
        }
      ]
    },
    {
      "title": "Mentoria em Backend Completo",
      "cards": [
        {
          "title": "Backend Completo",
          "badge": "nível avançado",
          "status": "Disponível",
          "vagas": "2",
          "thumbnail": "http://codigodozero.com/webdata/imageteste.png",
          "description": "Mentoria focada em backend profissional com práticas modernas, segurança e escalabilidade.",
          "benefits": [
            "APIs RESTful e GraphQL na prática",
            "Banco de dados relacionais e NoSQL",
            "JWT, OAuth2 e autenticação avançada",
            "Testes automatizados e integração contínua",
            "Acompanhamento técnico com feedbacks"
          ],
          "action_button": "Fazer aula grátis",
          "highlight": true
        }
      ]
    },
    {
      "title": "Mentoria em Frontend com React",
      "cards": [
        {
          "title": "Frontend com React",
          "badge": "popular",
          "status": "Indisponível",
          "vagas": "0",
          "thumbnail": "http://codigodozero.com/webdata/imageteste.png",
          "description": "Mentoria para dominar React, hooks, roteamento, context API e otimizações.",
          "benefits": [
            "Componentização e arquitetura moderna",
            "Styled-components, Tailwind e design system",
            "Conceitos avançados de estado e performance",
            "Integração com APIs e autenticação segura",
            "Simulados e desafios com correção detalhada"
          ],
          "action_button": "Fazer aula grátis",
          "highlight": false
        }
      ]
    },
    {
      "title": "Mentoria em Desenvolvimento de Games com Unity",
      "cards": [
        {
          "title": "Game Dev com Unity",
          "badge": "novo curso",
          "status": "Indisponível",
          "vagas": "0",
          "thumbnail": "http://codigodozero.com/webdata/imageteste.png",
          "description": "Mentoria prática para criação de jogos 2D e 3D com Unity e C#, desde os fundamentos até projetos completos.",
          "benefits": [
            "Criação de jogos 2D e 3D com Unity",
            "Programação de gameplay com C#",
            "Design de níveis e mecânicas interativas",
            "Publicação na Steam, Itch.io e mobile",
            "Aulas com exercícios e projetos guiados"
          ],
          "action_button": "Fazer aula grátis",
          "highlight": true
        }
      ]
    },
    {
      "title": "Mentoria em Desenvolvimento de Apps Mobile",
      "cards": [
        {
          "title": "Apps Mobile com Flutter e React Native",
          "badge": "mobile dev",
          "status": "Indisponível",
          "vagas": "0",
          "thumbnail": "http://codigodozero.com/webdata/imageteste.png",
          "description": "Aprenda a criar apps nativos e híbridos com Flutter e React Native, com foco em performance e design moderno.",
          "benefits": [
            "Projetos completos para Android e iOS",
            "Integração com APIs e bancos de dados",
            "Navegação, autenticação e animações fluidas",
            "Publicação nas lojas Google Play e App Store",
            "Mentoria prática com acompanhamento individual"
          ],
          "action_button": "Fazer aula grátis",
          "highlight": true
        }
      ]
    }
  ]
}
